Metadata-Version: 2.1
Name: dsu-data-structure
Version: 1.1.0
Summary: Disjoint set union structure implementation for Python 3.
Home-page: https://github.com/d1mav0lk0v/dsu_data_structure/
Author: Dmitry Volkov
Author-email: d1mav0lk0v@yandex.ru
License: MIT License, see LICENSE file
Download-URL: https://github.com/d1mav0lk0v/dsu_data_structure/zipball/master/
Platform: UNKNOWN
Classifier: Programming Language :: Python :: 3
Classifier: License :: OSI Approved :: MIT License
Classifier: Operating System :: OS Independent
License-File: LICENSE
